nexify-0.7.3.dist-info/METADATA
nexify-0.7.3.dist-info/WHEEL
nexify-0.7.3.dist-info/entry_points.txt
nexify/__init__.py
nexify/applications.py
nexify/cli/__init__.py
nexify/cli/application.py
nexify/cli/deploy/__init__.py
nexify/cli/deploy/constants.py
nexify/cli/deploy/environ.py
nexify/cli/deploy/package.py
nexify/cli/deploy/types.py
nexify/cli/exceptions.py
nexify/cli/init.py
nexify/convertors.py
nexify/dependencies/__init__.py
nexify/dependencies/models.py
nexify/dependencies/utils.py
nexify/encoders.py
nexify/exception_handlers.py
nexify/exceptions.py
nexify/middleware/__init__.py
nexify/models.py
nexify/openapi/__init__.py
nexify/openapi/constants.py
nexify/openapi/docs.py
nexify/openapi/models.py
nexify/openapi/utils.py
nexify/operation.py
nexify/param_functions.py
nexify/params.py
nexify/py.typed
nexify/responses.py
nexify/routing.py
nexify/schedule.py
nexify/status.py
nexify/templates/basic/.gitignore
nexify/templates/basic/main.py
nexify/templates/basic/nexify.json
nexify/templates/basic/requirements.txt
nexify/types.py
nexify/utils.py
nexify-0.7.3.dist-info/RECORD
